CHANGES
LICENSE
MANIFEST.in
README.rst
fork.py
setup.py
test_fork.py
fork.egg-info/PKG-INFO
fork.egg-info/SOURCES.txt
fork.egg-info/dependency_links.txt
fork.egg-info/not-zip-safe
fork.egg-info/top_level.txt