Metadata-Version: 1.1
Name: fork
Version: 0.1
Summary: A Python package for doing subprocess easily.
Home-page: https://github.com/fengsp/fork
Author: Shipeng Feng
Author-email: fsp261@gmail.com
License: BSD
Platform: UNKNOWN
Classifier: Development Status :: 4 - Beta
Classifier: Intended Audience :: Developers
Classifier: License :: OSI Approved :: BSD License
Classifier: Programming Language :: Python
